{
  "db_name": "PostgreSQL",
  "query": "\n        SELECT url, content_hash\n        FROM crawl_urls\n        WHERE id = $1 AND crawl_id = $2\n        ",
  "describe": {
    "columns": [
      {
        "ordinal": 0,
        "name": "url",
        "type_info": "Text"
      },
      {
        "ordinal": 1,
        "name": "content_hash",
        "type_info": "Bytea"
      }
    ],
    "parameters": {
      "Left": [
        "Uuid",
        "Uuid"
      ]
    },
    "nullable": [
      false,
      true
    ]
  },
  "hash": "78b443f1ec3f9ba7402591b952b1b0501897a5b7d0e8b861f1e8b778dbfce209"
}
